{
  "annotations": {
    "changelogDate": "20250914142332"
  },
  "applications": "*",
  "dto": "mapstruct",
  "fields": [
    {
      "fieldName": "deploymentDate",
      "fieldType": "Instant"
    },
    {
      "fieldName": "status",
      "fieldType": "DeploymentStatus",
      "fieldValues": "SUCCESS,FAILED,IN_PROGRESS"
    },
    {
      "fieldName": "logs",
      "fieldType": "TextBlob"
    },
    {
      "fieldName": "addendum",
      "fieldType": "String",
      "fieldValidateRules": ["maxlength"],
      "fieldValidateRulesMaxlength": "4000"
    }
  ],
  "jpaMetamodelFiltering": true,
  "name": "Deployment",
  "pagination": "pagination",
  "relationships": [
    {
      "otherEntityName": "user",
      "relationshipName": "deployedBy",
      "relationshipSide": "left",
      "relationshipType": "many-to-one",
      "relationshipWithBuiltInEntity": true
    },
    {
      "otherEntityField": "name",
      "otherEntityName": "deliverable",
      "relationshipName": "deliverable",
      "relationshipSide": "right",
      "relationshipType": "many-to-one"
    }
  ],
  "searchEngine": "no",
  "service": "serviceImpl"
}
